tc4/__init__.py
ASHTEAM-0.2.dist-info/METADATA
ASHTEAM-0.2.dist-info/WHEEL
ASHTEAM-0.2.dist-info/top_level.txt
ASHTEAM-0.2.dist-info/RECORD
