Metadata-Version: 2.1
Name: ASHTEAM
Version: 0.2
Summary: A powerful encryption libraries in Python created by the TC4 team
Home-page: UNKNOWN
Author: ASHTEAM
License: UNKNOWN
Platform: UNKNOWN
Classifier: Programming Language :: Python :: 3
